tkxterm/__init__.py
tkxterm/_parser.py
tkxterm/command.py
tkxterm/tkxterm.py
tkxterm-1.0.3.dist-info/METADATA
tkxterm-1.0.3.dist-info/WHEEL
tkxterm-1.0.3.dist-info/licenses/LICENSE
tkxterm-1.0.3.dist-info/RECORD
