Metadata-Version: 2.3
Name: tkxterm
Version: 1.0.3
Summary: Use XTerm embedded in a Tkinter frame, passing to it strings and commands and receving the exit code of the commands
Project-URL: Homepage, https://github.com/Church-17/tkxterm
Author-email: Matteo Chiesa <matteo.chiesa.mc@gmail.com>
Maintainer-email: Matteo Chiesa <matteo.chiesa.mc@gmail.com>
License:                     GNU GENERAL PUBLIC LICENSE
License-File: LICENSE
Keywords: bash,frame,terminal,tk,tkinter,ttk,xterm
Classifier: Development Status :: 4 - Beta
Classifier: Intended Audience :: Developers
Classifier: License :: OSI Approved :: GNU General Public License v3 (GPLv3)
Classifier: Operating System :: POSIX :: Linux
Classifier: Programming Language :: Python
Classifier: Programming Language :: Python :: 3
Requires-Python: >=3.10
